{"cameraMode":{"drawMode":0,"name":"Shaded","section":"Shading Mode"},"sceneLighting":true,"audioPlay":false,"sceneViewState":{"m_AlwaysRefresh":false,"showFog":true,"showSkybox":true,"showFlares":true,"showImageEffects":true,"showParticleSystems":true,"showVisualEffectGraphs":true,"m_FxEnabled":true},"in2DMode":false,"pivot":{"x":102.6292953491211,"y":4.861220359802246,"z":9.045768737792969},"rotation":{"x":-0.08527611196041107,"y":0.39993855357170107,"z":-0.03751207888126373,"w":-0.9116690158843994},"size":6.559638500213623,"orthographic":false}